{"index.md":"DdbrVtOM","na_2004_course-content.md":"D1fxEjCV","na_2004_course-info.md":"BX-2TTKY","na_2005_course-content.md":"B6spVFTg","na_2005_course-info.md":"sHP7Yo7d","na_2009_course-content.md":"DWnKmXz8","na_2009_course-info.md":"C8DpgBaO","na_2012_course-content.md":"BWkRatYY","na_2012_course-info.md":"B6iggJJT","na_2013_course-content.md":"WpI9FQbG","na_2013_course-info.md":"CpZ5ZG36","na_2014_course-content.md":"Bqn_uoqT","na_2014_course-info.md":"BObi2sgw","na_2015_course-content.md":"B_e5RyAK","na_2016_course-content.md":"CVSunwyN","na_2018_course-content.md":"HNrDwOzl","na_2020_course-content.md":"DzVQcc4S","na_2020_course-info.md":"CRol506H","na_2021_course-content.md":"C56tXtBH","na_2021_course-info.md":"C8RMI0sp","na_2022_course-content.md":"BIkswi-U","na_2022_course-info.md":"BEadT4-t","na_2023_course-content.md":"CP5LTDsJ","na_2023_course-info.md":"CHYQMAft","na_2024_course-content.md":"CmCGu0Pa","na_2024_course-info.md":"C8d_0-7c","na_2025_course-content.md":"DRNCp_F7","na_2025_course-info.md":"BKJGSr5X","na_index.md":"DG75kK0K","recommended-books.md":"OXu8-Hv-","related-links.md":"H079tKs4","sa_2004_course-content.md":"DhlWiGXS","sa_2004_course-info.md":"IkGwdJ68","sa_2005_course-content.md":"CqgCDR-r","sa_2005_course-info.md":"DjWvYBPN","sa_2006_course-content.md":"BGEplto2","sa_2006_course-info.md":"Der5s41C","sa_2007_course-content.md":"CrRlLd9A","sa_2007_course-info.md":"Rb-GuxFa","sa_2008_course-content.md":"C03bHRZu","sa_2008_course-info.md":"CPHIeKjB","sa_2009_course-content.md":"DTs6Yqlp","sa_2009_course-info.md":"DxqZGI6S","sa_2010_course-content.md":"BbGrga7k","sa_2010_course-info.md":"DkhWQBiF","sa_2011_course-content.md":"Ci7bXMk6","sa_2011_course-info.md":"BCE6Ih6b","sa_2012_course-content.md":"Dt2ZqhVN","sa_2012_course-info.md":"B740Pjvd","sa_2013_course-content.md":"Bv1IO4lJ","sa_2013_course-info.md":"CmYinnlc","sa_2014_course-content.md":"CCRE5lkY","sa_2014_course-info.md":"YBC7j_u8","sa_2015_course-content.md":"B-9m45QA","sa_2015_course-info.md":"r95VbZbu","sa_2016_course-content.md":"Bn6V-q9Y","sa_2016_course-info.md":"DbTDq6QJ","sa_2017_course-content.md":"B8-Rw87b","sa_2017_course-info.md":"CLyWoIzN","sa_2018_course-content.md":"I6nuBOWy","sa_2018_course-info.md":"BsPyvaJ_","sa_2019_course-content.md":"CqAMGoQB","sa_2019_course-info.md":"DG5Vy4PB","sa_2020_course-content.md":"D1WvhgNN","sa_2020_course-info.md":"CSnpfusc","sa_2021_course-content.md":"CfOfHfYT","sa_2021_course-info.md":"MWQjfsJs","sa_2022_course-content.md":"CMunlOHI","sa_2022_course-info.md":"D8_z5M_R","sa_2023_course-content.md":"BBO5wbyt","sa_2023_course-info.md":"BebmCQUO","sa_2024_course-content.md":"D2p60Vf-","sa_2024_course-info.md":"Cz1S4Dsl","sa_2025_course-content.md":"D4mqXLPS","sa_2025_course-info.md":"DbWJf1b-","sa_index.md":"BfHChe39","ta-information.md":"CtPHO0J5"}
